pulumi_gcp/__init__.py
pulumi_gcp/_inputs.py
pulumi_gcp/_utilities.py
pulumi_gcp/provider.py
pulumi_gcp/pulumi-plugin.json
pulumi_gcp/py.typed
pulumi_gcp/accessapproval/__init__.py
pulumi_gcp/accessapproval/get_folder_service_account.py
pulumi_gcp/accessapproval/get_organization_service_account.py
pulumi_gcp/accessapproval/get_project_service_account.py
pulumi_gcp/accesscontextmanager/__init__.py
pulumi_gcp/accesscontextmanager/_inputs.py
pulumi_gcp/accesscontextmanager/access_level.py
pulumi_gcp/accesscontextmanager/access_level_condition.py
pulumi_gcp/accesscontextmanager/access_levels.py
pulumi_gcp/accesscontextmanager/access_policy.py
pulumi_gcp/accesscontextmanager/access_policy_iam_binding.py
pulumi_gcp/accesscontextmanager/access_policy_iam_member.py
pulumi_gcp/accesscontextmanager/access_policy_iam_policy.py
pulumi_gcp/accesscontextmanager/authorized_orgs_desc.py
pulumi_gcp/accesscontextmanager/egress_policy.py
pulumi_gcp/accesscontextmanager/gcp_user_access_binding.py
pulumi_gcp/accesscontextmanager/get_access_policy.py
pulumi_gcp/accesscontextmanager/get_access_policy_iam_policy.py
pulumi_gcp/accesscontextmanager/ingress_policy.py
pulumi_gcp/accesscontextmanager/outputs.py
pulumi_gcp/accesscontextmanager/service_perimeter.py
pulumi_gcp/accesscontextmanager/service_perimeter_dry_run_egress_policy.py
pulumi_gcp/accesscontextmanager/service_perimeter_dry_run_ingress_policy.py
pulumi_gcp/accesscontextmanager/service_perimeter_dry_run_resource.py
pulumi_gcp/accesscontextmanager/service_perimeter_egress_policy.py
pulumi_gcp/accesscontextmanager/service_perimeter_ingress_policy.py
pulumi_gcp/accesscontextmanager/service_perimeter_resource.py
pulumi_gcp/accesscontextmanager/service_perimeters.py
pulumi_gcp/activedirectory/__init__.py
pulumi_gcp/activedirectory/domain.py
pulumi_gcp/activedirectory/domain_trust.py
pulumi_gcp/activedirectory/peering.py
pulumi_gcp/alloydb/__init__.py
pulumi_gcp/alloydb/_inputs.py
pulumi_gcp/alloydb/backup.py
pulumi_gcp-9.4.0.dist-info/METADATA
pulumi_gcp-9.4.0.dist-info/WHEEL
pulumi_gcp-9.4.0.dist-info/top_level.txt
pulumi_gcp-9.4.0.dist-info/RECORD
